fastapi_casbin_auth/__init__.py
fastapi_casbin_auth/middleware.py
fastapi_casbin_auth-1.5.0.data/data/README.md
fastapi_casbin_auth-1.5.0.data/data/requirements.txt
fastapi_casbin_auth-1.5.0.dist-info/licenses/LICENSE
fastapi_casbin_auth-1.5.0.dist-info/METADATA
fastapi_casbin_auth-1.5.0.dist-info/WHEEL
fastapi_casbin_auth-1.5.0.dist-info/top_level.txt
fastapi_casbin_auth-1.5.0.dist-info/RECORD
