Metadata-Version: 2.4
Name: fastapi-casbin-auth
Version: 1.5.0
Summary: An authorization middleware for FastAPI that supports ACL, RBAC, ABAC, based on PyCasbin
Home-page: https://github.com/officialpycasbin/fastapi-casbin-auth
Author: Casbin
Author-email: admin@casbin.org
License: Apache 2.0
Keywords: fastapi,starlette,middleware,pycasbin,casbin,auth,authz,acl,rbac,abac,access control,authorization,permission
Classifier: Programming Language :: Python :: 3.9
Classifier: Programming Language :: Python :: 3.10
Classifier: Programming Language :: Python :: 3.11
Classifier: Programming Language :: Python :: 3.12
Classifier: License :: OSI Approved :: Apache Software License
Classifier: Operating System :: OS Independent
Requires-Python: >=3.6
License-File: LICENSE
Requires-Dist: annotated-doc==0.0.4
Requires-Dist: annotated-types==0.7.0
Requires-Dist: anyio==4.11.0
Requires-Dist: bracex==2.6
Requires-Dist: fastapi==0.121.2
Requires-Dist: idna==3.11
Requires-Dist: pycasbin==2.6.0
Requires-Dist: pydantic==2.12.4
Requires-Dist: pydantic-core==2.41.5
Requires-Dist: simpleeval==1.0.3
Requires-Dist: sniffio==1.3.1
Requires-Dist: starlette==0.49.3
Requires-Dist: typing-extensions==4.15.0
Requires-Dist: typing-inspection==0.4.2
Requires-Dist: wcmatch==10.1
Dynamic: author
Dynamic: author-email
Dynamic: classifier
Dynamic: description
Dynamic: description-content-type
Dynamic: home-page
Dynamic: keywords
Dynamic: license
Dynamic: license-file
Dynamic: requires-dist
Dynamic: requires-python
Dynamic: summary
